setup.cfg
setup.py
zmei/__init__.py
zmei/i18n.py
zmei/json.py
zmei/react.py
zmei/serializer.py
zmei/views.py
zmei/crud/__init__.py
zmei/crud/templatetags/__init__.py
zmei/crud/templatetags/crud_utils.py
zmei_utils.egg-info/PKG-INFO
zmei_utils.egg-info/SOURCES.txt
zmei_utils.egg-info/dependency_links.txt
zmei_utils.egg-info/not-zip-safe
zmei_utils.egg-info/requires.txt
zmei_utils.egg-info/top_level.txt