Metadata-Version: 1.0
Name: zmei-utils
Version: 0.1.15
Summary: Intuitive web-framework, based on rock-solid opensource components.
Home-page: https://github.com/Negative Space OU/zmei
Author: Alex Rudakov
Author-email: ribozz@gmail.com
License: UNKNOWN
Platform: UNKNOWN
